{
  "users": [
    {
      "id": "user-admin-001",
      "username": "admin",
      "password": "$2b$10$r/W9GsDzkqUfX4K2GeXFEOXmW5RiQ3Zzxwc3b8mwZ8yWosMK.Da/2",
      "email": "admin@portfolio-crm.com",
      "createdAt": "2024-01-01T00:00:00.000Z",
      "updatedAt": "2024-01-01T00:00:00.000Z"
    }
  ],
  "customers": [
    {
      "id": "customer-001",
      "firstName": "Max",
      "lastName": "Müller",
      "email": "max.müller@example.com",
      "phone": "+49 143 4183996",
      "company": "Tech Solutions GmbH",
      "status": "ACTIVE",
      "address": "Hauptstraße 10, 10115 Berlin",
      "notes": "VIP Customer - High Priority",
      "createdAt": "2023-12-31T23:00:00.000Z",
      "updatedAt": "2023-12-31T23:00:00.000Z"
    },
    {
      "id": "customer-002",
      "firstName": "Lisa",
      "lastName": "Schmidt",
      "email": "lisa.schmidt@example.com",
      "phone": "+49 794 1751643",
      "company": "Digital Innovation AG",
      "status": "INACTIVE",
      "createdAt": "2024-01-01T23:00:00.000Z",
      "updatedAt": "2024-01-01T23:00:00.000Z"
    },
    {
      "id": "customer-003",
      "firstName": "Michael",
      "lastName": "Schneider",
      "email": "michael.schneider@example.com",
      "phone": "+49 564 2157789",
      "company": "Cloud Services Ltd",
      "status": "LEAD",
      "createdAt": "2024-01-02T23:00:00.000Z",
      "updatedAt": "2024-01-02T23:00:00.000Z"
    },
    {
      "id": "customer-004",
      "firstName": "Anna",
      "lastName": "Fischer",
      "email": "anna.fischer@example.com",
      "phone": "+49 593 2264791",
      "company": "Software Experts",
      "status": "ACTIVE",
      "address": "Hauptstraße 13, 10145 Berlin",
      "createdAt": "2024-01-03T23:00:00.000Z",
      "updatedAt": "2024-01-03T23:00:00.000Z"
    },
    {
      "id": "customer-005",
      "firstName": "Thomas",
      "lastName": "Weber",
      "email": "thomas.weber@example.com",
      "phone": "+49 806 9221072",
      "company": "Web Development Co",
      "status": "INACTIVE",
      "notes": "VIP Customer - High Priority",
      "createdAt": "2024-01-04T23:00:00.000Z",
      "updatedAt": "2024-01-04T23:00:00.000Z"
    },
    {
      "id": "customer-006",
      "firstName": "Sarah",
      "lastName": "Meyer",
      "email": "sarah.meyer@example.com",
      "phone": "+49 676 9073455",
      "company": "Data Analytics GmbH",
      "status": "LEAD",
      "createdAt": "2024-01-05T23:00:00.000Z",
      "updatedAt": "2024-01-05T23:00:00.000Z"
    },
    {
      "id": "customer-007",
      "firstName": "Daniel",
      "lastName": "Wagner",
      "email": "daniel.wagner@example.com",
      "phone": "+49 557 5322160",
      "company": "Mobile Apps AG",
      "status": "ACTIVE",
      "address": "Hauptstraße 16, 10175 Berlin",
      "createdAt": "2024-01-06T23:00:00.000Z",
      "updatedAt": "2024-01-06T23:00:00.000Z"
    },
    {
      "id": "customer-008",
      "firstName": "Julia",
      "lastName": "Becker",
      "email": "julia.becker@example.com",
      "phone": "+49 259 5783526",
      "company": "IT Consulting",
      "status": "INACTIVE",
      "createdAt": "2024-01-07T23:00:00.000Z",
      "updatedAt": "2024-01-07T23:00:00.000Z"
    },
    {
      "id": "customer-009",
      "firstName": "Markus",
      "lastName": "Schulz",
      "email": "markus.schulz@example.com",
      "phone": "+49 814 6404027",
      "company": "E-Commerce Solutions",
      "status": "LEAD",
      "notes": "VIP Customer - High Priority",
      "createdAt": "2024-01-08T23:00:00.000Z",
      "updatedAt": "2024-01-08T23:00:00.000Z"
    },
    {
      "id": "customer-010",
      "firstName": "Laura",
      "lastName": "Hoffmann",
      "email": "laura.hoffmann@example.com",
      "phone": "+49 783 7749643",
      "company": "Marketing Digital",
      "status": "ACTIVE",
      "address": "Hauptstraße 19, 10205 Berlin",
      "createdAt": "2024-01-09T23:00:00.000Z",
      "updatedAt": "2024-01-09T23:00:00.000Z"
    },
    {
      "id": "customer-011",
      "firstName": "Sebastian",
      "lastName": "Koch",
      "email": "sebastian.koch@example.com",
      "phone": "+49 159 6282988",
      "company": "Design Studio",
      "status": "INACTIVE",
      "createdAt": "2024-01-10T23:00:00.000Z",
      "updatedAt": "2024-01-10T23:00:00.000Z"
    },
    {
      "id": "customer-012",
      "firstName": "Maria",
      "lastName": "Bauer",
      "email": "maria.bauer@example.com",
      "phone": "+49 796 2758705",
      "company": "Consulting Partners",
      "status": "LEAD",
      "createdAt": "2024-01-11T23:00:00.000Z",
      "updatedAt": "2024-01-11T23:00:00.000Z"
    },
    {
      "id": "customer-013",
      "firstName": "Christian",
      "lastName": "Richter",
      "email": "christian.richter@example.com",
      "phone": "+49 616 2228594",
      "company": "Business Solutions",
      "status": "ACTIVE",
      "address": "Hauptstraße 22, 10235 Berlin",
      "notes": "VIP Customer - High Priority",
      "createdAt": "2024-01-12T23:00:00.000Z",
      "updatedAt": "2024-01-12T23:00:00.000Z"
    },
    {
      "id": "customer-014",
      "firstName": "Sophie",
      "lastName": "Klein",
      "email": "sophie.klein@example.com",
      "phone": "+49 785 4438771",
      "company": "Enterprise Systems",
      "status": "INACTIVE",
      "createdAt": "2024-01-13T23:00:00.000Z",
      "updatedAt": "2024-01-13T23:00:00.000Z"
    },
    {
      "id": "customer-015",
      "firstName": "Andreas",
      "lastName": "Wolf",
      "email": "andreas.wolf@example.com",
      "phone": "+49 335 8345977",
      "company": "Development Group",
      "status": "LEAD",
      "createdAt": "2024-01-14T23:00:00.000Z",
      "updatedAt": "2024-01-14T23:00:00.000Z"
    }
  ],
  "deals": [
    {
      "id": "deal-001",
      "title": "Website Redesign",
      "description": "Website Redesign project for Tech Solutions GmbH",
      "value": 95691,
      "currency": "EUR",
      "status": "LEAD",
      "customerId": "customer-001",
      "startDate": "2024-01-07T23:00:00.000Z",
      "notes": "Urgent - High Priority Deal",
      "createdAt": "2023-12-31T23:00:00.000Z",
      "updatedAt": "2023-12-31T23:00:00.000Z"
    },
    {
      "id": "deal-002",
      "title": "Mobile App Development",
      "description": "Mobile App Development project for Digital Innovation AG",
      "value": 19484,
      "currency": "EUR",
      "status": "IN_PROGRESS",
      "customerId": "customer-002",
      "startDate": "2024-01-08T23:00:00.000Z",
      "createdAt": "2024-01-01T23:00:00.000Z",
      "updatedAt": "2024-01-01T23:00:00.000Z"
    },
    {
      "id": "deal-003",
      "title": "Cloud Migration",
      "description": "Cloud Migration project for Cloud Services Ltd",
      "value": 80486,
      "currency": "EUR",
      "status": "WON",
      "customerId": "customer-003",
      "startDate": "2024-01-09T23:00:00.000Z",
      "endDate": "2024-05-09T22:00:00.000Z",
      "createdAt": "2024-01-02T23:00:00.000Z",
      "updatedAt": "2024-01-02T23:00:00.000Z"
    },
    {
      "id": "deal-004",
      "title": "E-Commerce Platform",
      "description": "E-Commerce Platform project for Software Experts",
      "value": 76679,
      "currency": "EUR",
      "status": "LOST",
      "customerId": "customer-004",
      "startDate": "2024-01-10T23:00:00.000Z",
      "endDate": "2024-04-10T22:00:00.000Z",
      "createdAt": "2024-01-03T23:00:00.000Z",
      "updatedAt": "2024-01-03T23:00:00.000Z"
    },
    {
      "id": "deal-005",
      "title": "CRM System Implementation",
      "description": "CRM System Implementation project for Web Development Co",
      "value": 91919,
      "currency": "EUR",
      "status": "LEAD",
      "customerId": "customer-005",
      "startDate": "2024-01-11T23:00:00.000Z",
      "createdAt": "2024-01-04T23:00:00.000Z",
      "updatedAt": "2024-01-04T23:00:00.000Z"
    },
    {
      "id": "deal-006",
      "title": "Marketing Campaign",
      "description": "Marketing Campaign project for Data Analytics GmbH",
      "value": 71676,
      "currency": "EUR",
      "status": "IN_PROGRESS",
      "customerId": "customer-006",
      "startDate": "2024-02-12T23:00:00.000Z",
      "notes": "Urgent - High Priority Deal",
      "createdAt": "2024-02-05T23:00:00.000Z",
      "updatedAt": "2024-02-05T23:00:00.000Z"
    },
    {
      "id": "deal-007",
      "title": "SEO Optimization",
      "description": "SEO Optimization project for Mobile Apps AG",
      "value": 89024,
      "currency": "EUR",
      "status": "WON",
      "customerId": "customer-007",
      "startDate": "2024-02-13T23:00:00.000Z",
      "endDate": "2024-07-13T22:00:00.000Z",
      "createdAt": "2024-02-06T23:00:00.000Z",
      "updatedAt": "2024-02-06T23:00:00.000Z"
    },
    {
      "id": "deal-008",
      "title": "Data Analytics Dashboard",
      "description": "Data Analytics Dashboard project for IT Consulting",
      "value": 37238,
      "currency": "EUR",
      "status": "LOST",
      "customerId": "customer-008",
      "startDate": "2024-02-14T23:00:00.000Z",
      "endDate": "2024-06-14T22:00:00.000Z",
      "createdAt": "2024-02-07T23:00:00.000Z",
      "updatedAt": "2024-02-07T23:00:00.000Z"
    },
    {
      "id": "deal-009",
      "title": "API Integration",
      "description": "API Integration project for E-Commerce Solutions",
      "value": 80996,
      "currency": "EUR",
      "status": "LEAD",
      "customerId": "customer-009",
      "startDate": "2024-02-15T23:00:00.000Z",
      "createdAt": "2024-02-08T23:00:00.000Z",
      "updatedAt": "2024-02-08T23:00:00.000Z"
    },
    {
      "id": "deal-010",
      "title": "Security Audit",
      "description": "Security Audit project for Marketing Digital",
      "value": 99961,
      "currency": "EUR",
      "status": "IN_PROGRESS",
      "customerId": "customer-010",
      "startDate": "2024-02-16T23:00:00.000Z",
      "createdAt": "2024-02-09T23:00:00.000Z",
      "updatedAt": "2024-02-09T23:00:00.000Z"
    },
    {
      "id": "deal-011",
      "title": "Performance Optimization",
      "description": "Performance Optimization project for Design Studio",
      "value": 46794,
      "currency": "EUR",
      "status": "WON",
      "customerId": "customer-011",
      "startDate": "2024-03-17T23:00:00.000Z",
      "endDate": "2024-08-17T22:00:00.000Z",
      "notes": "Urgent - High Priority Deal",
      "createdAt": "2024-03-10T23:00:00.000Z",
      "updatedAt": "2024-03-10T23:00:00.000Z"
    },
    {
      "id": "deal-012",
      "title": "Social Media Strategy",
      "description": "Social Media Strategy project for Consulting Partners",
      "value": 37362,
      "currency": "EUR",
      "status": "LOST",
      "customerId": "customer-012",
      "startDate": "2024-03-18T23:00:00.000Z",
      "endDate": "2024-06-18T22:00:00.000Z",
      "createdAt": "2024-03-11T23:00:00.000Z",
      "updatedAt": "2024-03-11T23:00:00.000Z"
    },
    {
      "id": "deal-013",
      "title": "Brand Identity",
      "description": "Brand Identity project for Business Solutions",
      "value": 50502,
      "currency": "EUR",
      "status": "LEAD",
      "customerId": "customer-013",
      "startDate": "2024-03-19T23:00:00.000Z",
      "createdAt": "2024-03-12T23:00:00.000Z",
      "updatedAt": "2024-03-12T23:00:00.000Z"
    },
    {
      "id": "deal-014",
      "title": "Content Management System",
      "description": "Content Management System project for Enterprise Systems",
      "value": 27964,
      "currency": "EUR",
      "status": "IN_PROGRESS",
      "customerId": "customer-014",
      "startDate": "2024-03-20T23:00:00.000Z",
      "createdAt": "2024-03-13T23:00:00.000Z",
      "updatedAt": "2024-03-13T23:00:00.000Z"
    },
    {
      "id": "deal-015",
      "title": "Email Marketing Platform",
      "description": "Email Marketing Platform project for Development Group",
      "value": 98845,
      "currency": "EUR",
      "status": "WON",
      "customerId": "customer-015",
      "startDate": "2024-03-21T23:00:00.000Z",
      "endDate": "2024-08-21T22:00:00.000Z",
      "createdAt": "2024-03-14T23:00:00.000Z",
      "updatedAt": "2024-03-14T23:00:00.000Z"
    },
    {
      "id": "deal-016",
      "title": "Customer Portal",
      "description": "Customer Portal project for Tech Solutions GmbH",
      "value": 74671,
      "currency": "EUR",
      "status": "LOST",
      "customerId": "customer-001",
      "startDate": "2024-04-22T22:00:00.000Z",
      "endDate": "2024-06-22T22:00:00.000Z",
      "notes": "Urgent - High Priority Deal",
      "createdAt": "2024-04-15T22:00:00.000Z",
      "updatedAt": "2024-04-15T22:00:00.000Z"
    },
    {
      "id": "deal-017",
      "title": "Inventory Management",
      "description": "Inventory Management project for Digital Innovation AG",
      "value": 37318,
      "currency": "EUR",
      "status": "LEAD",
      "customerId": "customer-002",
      "startDate": "2024-04-23T22:00:00.000Z",
      "createdAt": "2024-04-16T22:00:00.000Z",
      "updatedAt": "2024-04-16T22:00:00.000Z"
    },
    {
      "id": "deal-018",
      "title": "Payment Gateway Integration",
      "description": "Payment Gateway Integration project for Cloud Services Ltd",
      "value": 59022,
      "currency": "EUR",
      "status": "IN_PROGRESS",
      "customerId": "customer-003",
      "startDate": "2024-04-24T22:00:00.000Z",
      "createdAt": "2024-04-17T22:00:00.000Z",
      "updatedAt": "2024-04-17T22:00:00.000Z"
    },
    {
      "id": "deal-019",
      "title": "Business Intelligence System",
      "description": "Business Intelligence System project for Software Experts",
      "value": 67967,
      "currency": "EUR",
      "status": "WON",
      "customerId": "customer-004",
      "startDate": "2024-04-25T22:00:00.000Z",
      "endDate": "2024-10-25T22:00:00.000Z",
      "createdAt": "2024-04-18T22:00:00.000Z",
      "updatedAt": "2024-04-18T22:00:00.000Z"
    },
    {
      "id": "deal-020",
      "title": "Training Platform",
      "description": "Training Platform project for Web Development Co",
      "value": 31792,
      "currency": "EUR",
      "status": "LOST",
      "customerId": "customer-005",
      "startDate": "2024-04-26T22:00:00.000Z",
      "endDate": "2024-08-26T22:00:00.000Z",
      "createdAt": "2024-04-19T22:00:00.000Z",
      "updatedAt": "2024-04-19T22:00:00.000Z"
    },
    {
      "id": "deal-021",
      "title": "Support Ticketing System",
      "description": "Support Ticketing System project for Data Analytics GmbH",
      "value": 77659,
      "currency": "EUR",
      "status": "LEAD",
      "customerId": "customer-006",
      "startDate": "2024-05-27T22:00:00.000Z",
      "notes": "Urgent - High Priority Deal",
      "createdAt": "2024-05-20T22:00:00.000Z",
      "updatedAt": "2024-05-20T22:00:00.000Z"
    },
    {
      "id": "deal-022",
      "title": "Video Streaming Service",
      "description": "Video Streaming Service project for Mobile Apps AG",
      "value": 13718,
      "currency": "EUR",
      "status": "IN_PROGRESS",
      "customerId": "customer-007",
      "startDate": "2024-05-28T22:00:00.000Z",
      "createdAt": "2024-05-21T22:00:00.000Z",
      "updatedAt": "2024-05-21T22:00:00.000Z"
    },
    {
      "id": "deal-023",
      "title": "IoT Platform",
      "description": "IoT Platform project for IT Consulting",
      "value": 77435,
      "currency": "EUR",
      "status": "WON",
      "customerId": "customer-008",
      "startDate": "2024-05-29T22:00:00.000Z",
      "endDate": "2024-07-29T22:00:00.000Z",
      "createdAt": "2024-05-22T22:00:00.000Z",
      "updatedAt": "2024-05-22T22:00:00.000Z"
    },
    {
      "id": "deal-024",
      "title": "Blockchain Integration",
      "description": "Blockchain Integration project for E-Commerce Solutions",
      "value": 11624,
      "currency": "EUR",
      "status": "LOST",
      "customerId": "customer-009",
      "startDate": "2024-05-30T22:00:00.000Z",
      "endDate": "2024-11-30T23:00:00.000Z",
      "createdAt": "2024-05-23T22:00:00.000Z",
      "updatedAt": "2024-05-23T22:00:00.000Z"
    },
    {
      "id": "deal-025",
      "title": "AI Chatbot",
      "description": "AI Chatbot project for Marketing Digital",
      "value": 96898,
      "currency": "EUR",
      "status": "LEAD",
      "customerId": "customer-010",
      "startDate": "2024-05-31T22:00:00.000Z",
      "createdAt": "2024-05-24T22:00:00.000Z",
      "updatedAt": "2024-05-24T22:00:00.000Z"
    },
    {
      "id": "deal-026",
      "title": "Document Management",
      "description": "Document Management project for Design Studio",
      "value": 56270,
      "currency": "EUR",
      "status": "IN_PROGRESS",
      "customerId": "customer-011",
      "startDate": "2024-07-02T22:00:00.000Z",
      "notes": "Urgent - High Priority Deal",
      "createdAt": "2024-06-25T22:00:00.000Z",
      "updatedAt": "2024-06-25T22:00:00.000Z"
    },
    {
      "id": "deal-027",
      "title": "HR Management System",
      "description": "HR Management System project for Consulting Partners",
      "value": 77527,
      "currency": "EUR",
      "status": "WON",
      "customerId": "customer-012",
      "startDate": "2024-07-03T22:00:00.000Z",
      "endDate": "2024-10-03T22:00:00.000Z",
      "createdAt": "2024-06-26T22:00:00.000Z",
      "updatedAt": "2024-06-26T22:00:00.000Z"
    },
    {
      "id": "deal-028",
      "title": "Project Management Tool",
      "description": "Project Management Tool project for Business Solutions",
      "value": 44659,
      "currency": "EUR",
      "status": "LOST",
      "customerId": "customer-013",
      "startDate": "2024-07-04T22:00:00.000Z",
      "endDate": "2024-10-04T22:00:00.000Z",
      "createdAt": "2024-06-27T22:00:00.000Z",
      "updatedAt": "2024-06-27T22:00:00.000Z"
    },
    {
      "id": "deal-029",
      "title": "Collaboration Platform",
      "description": "Collaboration Platform project for Enterprise Systems",
      "value": 54418,
      "currency": "EUR",
      "status": "LEAD",
      "customerId": "customer-014",
      "startDate": "2024-06-07T22:00:00.000Z",
      "createdAt": "2024-05-31T22:00:00.000Z",
      "updatedAt": "2024-05-31T22:00:00.000Z"
    },
    {
      "id": "deal-030",
      "title": "Backup Solution",
      "description": "Backup Solution project for Development Group",
      "value": 86271,
      "currency": "EUR",
      "status": "IN_PROGRESS",
      "customerId": "customer-015",
      "startDate": "2024-06-08T22:00:00.000Z",
      "createdAt": "2024-06-01T22:00:00.000Z",
      "updatedAt": "2024-06-01T22:00:00.000Z"
    }
  ]
}